terragit/__init__.py
terragit/__main__.py
terragit/terracommand.py
terragit/terradocs.py
terragit/terragrunt.py
terragit/terrareport.py
terragit-0.2.1.dist-info/LICENCE.txt
terragit-0.2.1.dist-info/METADATA
terragit-0.2.1.dist-info/WHEEL
terragit-0.2.1.dist-info/entry_points.txt
terragit-0.2.1.dist-info/top_level.txt
terragit-0.2.1.dist-info/RECORD
