Metadata-Version: 2.1
Name: terragit
Version: 0.2.1
Summary: terragit package
Home-page: UNKNOWN
Author: amin
Author-email: amin.trabelsi@allence-tunisie.com
License: MIT
Keywords: terragit
Platform: UNKNOWN
Classifier: Development Status :: 5 - Production/Stable
Classifier: Operating System :: Microsoft :: Windows :: Windows 10
Classifier: License :: OSI Approved :: MIT License
Classifier: Programming Language :: Python :: 3
